sciplex/__init__.py
sciplex_core/__init__.py
sciplex_core/assets/icons/MaxMin.png
sciplex_core/assets/icons/TableFormula.png
sciplex_core/assets/icons/action_chat.png
sciplex_core/assets/icons/action_delete.png
sciplex_core/assets/icons/action_edit.png
sciplex_core/assets/icons/action_exec_mode.png
sciplex_core/assets/icons/action_execute.png
sciplex_core/assets/icons/action_export.png
sciplex_core/assets/icons/action_newnode.png
sciplex_core/assets/icons/action_python.png
sciplex_core/assets/icons/action_reset.png
sciplex_core/assets/icons/action_save.png
sciplex_core/assets/icons/action_workspace.png
sciplex_core/assets/icons/arithm.png
sciplex_core/assets/icons/barchart.png
sciplex_core/assets/icons/boolean.png
sciplex_core/assets/icons/boxplot.png
sciplex_core/assets/icons/change.png
sciplex_core/assets/icons/chat.png
sciplex_core/assets/icons/concat.png
sciplex_core/assets/icons/config.png
sciplex_core/assets/icons/corr.png
sciplex_core/assets/icons/csv.png
sciplex_core/assets/icons/cumsum.png
sciplex_core/assets/icons/cut.png
sciplex_core/assets/icons/data_array.png
sciplex_core/assets/icons/data_table.png
sciplex_core/assets/icons/dataset.png
sciplex_core/assets/icons/decisiontree.png
sciplex_core/assets/icons/delete.png
sciplex_core/assets/icons/diff.png
sciplex_core/assets/icons/drop.png
sciplex_core/assets/icons/encoder.png
sciplex_core/assets/icons/explorer_grey.png
sciplex_core/assets/icons/failed.png
sciplex_core/assets/icons/filter.png
sciplex_core/assets/icons/folder.png
sciplex_core/assets/icons/function.png
sciplex_core/assets/icons/grid.png
sciplex_core/assets/icons/group.png
sciplex_core/assets/icons/hammer.png
sciplex_core/assets/icons/histogram.png
sciplex_core/assets/icons/info.png
sciplex_core/assets/icons/input.png
sciplex_core/assets/icons/line.png
sciplex_core/assets/icons/linreg.png
sciplex_core/assets/icons/list.png
sciplex_core/assets/icons/logical.png
sciplex_core/assets/icons/map1d.png
sciplex_core/assets/icons/map2d.png
sciplex_core-0.1.2.dist-info/licenses/LICENSE
sciplex_core-0.1.2.dist-info/METADATA
sciplex_core-0.1.2.dist-info/WHEEL
sciplex_core-0.1.2.dist-info/top_level.txt
sciplex_core-0.1.2.dist-info/RECORD
