Metadata-Version: 2.4
Name: sciplex-core
Version: 0.1.2
Summary: Core logic for Sciplex visual programming - models, controllers, and utilities
Author-email: Sciplex Team <info@sciplex.de>
License: MIT
Project-URL: Homepage, https://sciplex.de/en/
Project-URL: Documentation, https://sciplex.de/en/
Project-URL: Repository, https://github.com/sciplex-app/sciplex_core.git
Keywords: data-science,visual-programming,workflow,nodes,core
Classifier: Development Status :: 3 - Alpha
Classifier: Intended Audience :: Science/Research
Classifier: Intended Audience :: Developers
Classifier: License :: OSI Approved :: MIT License
Classifier: Programming Language :: Python :: 3
Classifier: Programming Language :: Python :: 3.11
Classifier: Programming Language :: Python :: 3.12
Classifier: Topic :: Scientific/Engineering
Classifier: Topic :: Software Development :: Libraries :: Python Modules
Requires-Python: >=3.11
License-File: LICENSE
Requires-Dist: pandas>=2.2.0
Requires-Dist: numpy>=1.26.0
Requires-Dist: scikit-learn<2.0.0,>=1.6.0
Requires-Dist: xgboost>=3.0.0
Requires-Dist: networkx>=3.4.0
Requires-Dist: python-dotenv>=1.0.0
Requires-Dist: docstring_parser>=0.16
Requires-Dist: openpyxl>=3.1.0
Requires-Dist: numexpr>=2.11.0
Requires-Dist: plotly>=5.0.0
Provides-Extra: dev
Requires-Dist: pytest>=8.0.0; extra == "dev"
Requires-Dist: ruff>=0.8.4; extra == "dev"
Requires-Dist: mypy>=1.13.0; extra == "dev"
Dynamic: license-file
